{
  "name": "Political Science—Public Service, Bachelor of Arts",
  "url": "https://catalog.ucdavis.edu/departments-programs-degrees/political-science/political-science-public-service-ab/",
  "degree_type": "B.A.",
  "department": "Political Science",
  "description": "Office & Contact Information",
  "requirements": [
    {
      "heading": "General Requirements",
      "courses": [
        "POL 001",
        "POL 001Y",
        "POL 005",
        "POL 100",
        "POL 102",
        "POL 104",
        "POL 105",
        "POL 106",
        "POL 108",
        "POL 109",
        "POL 113",
        "POL 130",
        "POL 131",
        "POL 160",
        "POL 163"
      ],
      "units": "Units",
      "notes": []
    },
    {
      "heading": "Preparatory Subject Matter",
      "courses": [
        "POL 001",
        "POL 001Y",
        "POL 051",
        "POL 002",
        "POL 003",
        "POL 004",
        "POL 005",
        "POL 007",
        "POL 007V",
        "POL/CMN/SOC/PSC 012Y",
        "STA 013",
        "STA 013Y",
        "STA 032"
      ],
      "units": "4",
      "notes": [
        "Choose three:",
        "Choose one:",
        "Preparatory Subject Matter Subtotal"
      ]
    },
    {
      "heading": "Core Program",
      "courses": [
        "POL 100",
        "POL 102",
        "POL 104",
        "POL 105",
        "POL 106",
        "POL 108",
        "POL 109",
        "POL 113",
        "POL 114",
        "POL 180"
      ],
      "units": "12",
      "notes": [
        "Choose three:"
      ]
    },
    {
      "heading": "Internship",
      "courses": [
        "POL 192A",
        "POL 192B",
        "WAS 192"
      ],
      "units": "6",
      "notes": [
        "Choose one:"
      ]
    },
    {
      "heading": "Research Paper",
      "courses": [
        "WAS 193/POL 193W",
        "POL 193"
      ],
      "units": "2-4",
      "notes": []
    },
    {
      "heading": "Fields of Concentration",
      "courses": [],
      "units": "24",
      "notes": [
        "Select six upper division courses from two or three fields of concentration listed below with at least two courses in each field selected; at least 16 of the units must be in Political Science; No overlap between Core Program courses and Fields of Concentration allowed.",
        "Field (1) Policy Process",
        "Field (2) Policy Interpretation (Public/Pre-Law)",
        "Field (3) State & Local Policy",
        "Field (4) Foreign Policy",
        "Field (5) Environmental Policy",
        "Field (6) Economic Policy",
        "Field (7) Social Policy",
        "Field (8) Policy Analysis Tool",
        "Field (9) Honors Thesis",
        "Depth Subject Matter Subtotal"
      ]
    },
    {
      "heading": "General Requirements",
      "courses": [
        "POL 100",
        "POL 102",
        "POL 104",
        "POL 105",
        "POL 106",
        "POL 108",
        "POL 109",
        "POL 140A",
        "POL 160",
        "POL 162",
        "POL 163",
        "POL 164",
        "POL 165",
        "POL 165V",
        "POL 166",
        "POL 168",
        "POL 170",
        "POL 171",
        "POL 172",
        "POL 174",
        "POL 175",
        "POL 180",
        "POL 183",
        "POL 187",
        "POL 195",
        "ECN 130",
        "ECN 130Y",
        "ECN 131",
        "ECN 131V",
        "ECN 131Y"
      ],
      "units": "Units",
      "notes": []
    },
    {
      "heading": "General Requirements",
      "courses": [
        "POL 119",
        "POL 150",
        "POL 151",
        "POL 152",
        "POL 153",
        "POL 155"
      ],
      "units": "Units",
      "notes": []
    },
    {
      "heading": "General Requirements",
      "courses": [
        "POL 100",
        "POL 102",
        "POL 104",
        "ESP 173",
        "SOC 143A"
      ],
      "units": "Units",
      "notes": []
    },
    {
      "heading": "General Requirements",
      "courses": [
        "POL 122",
        "POL 130",
        "POL 131",
        "POL 132",
        "POL 134",
        "POL 139"
      ],
      "units": "Units",
      "notes": []
    },
    {
      "heading": "General Requirements",
      "courses": [
        "POL 107",
        "ESP 160",
        "ESP 161",
        "ESP 162",
        "ESP 166",
        "ESP 168A",
        "ESP 168B",
        "ESP 169",
        "ESP 171",
        "ESP 172",
        "ESP 173",
        "ESP 179"
      ],
      "units": "Units",
      "notes": []
    },
    {
      "heading": "General Requirements",
      "courses": [
        "ECN 100A",
        "ECN 100AV",
        "ECN 130",
        "ECN 130Y",
        "ECN 131",
        "ECN 131V",
        "ECN 131Y",
        "ECN 151A",
        "ECN 151B"
      ],
      "units": "Units",
      "notes": []
    },
    {
      "heading": "General Requirements",
      "courses": [
        "SOC/IRE 104",
        "SOC 124",
        "SOC 141",
        "SOC 150",
        "SOC 151",
        "SOC 155"
      ],
      "units": "Units",
      "notes": []
    },
    {
      "heading": "General Requirements",
      "courses": [
        "ECN 102",
        "ECN 140",
        "POL 114"
      ],
      "units": "Units",
      "notes": []
    },
    {
      "heading": "General Requirements",
      "courses": [
        "POL 194HA",
        "POL 194HB"
      ],
      "units": "Units",
      "notes": []
    }
  ],
  "specializations": [],
  "advising_notes": [
    "Field (9) Honors Thesis: Course List Code Title Units POL 194HASpecial Study for Honors Students4 POL 194HBSpecial Study for Honors Students4"
  ],
  "total_units": "68"
}